{"comparability":{"dataset_id":"nyc_tlc_yellow_2024","workload_id":"tlc_download_duckdb_native","timed_region_version":1,"cdf_revision":"5788609af065ce5ed0bb993ab545cce644ae9bf4+dirty","dependency_tuple":"Cargo.lock","host_class":"host-class-95da083e15eebd1c","os_toolchain":"rustc-1.97.1","io_mode":"warm"},"expected_host_class":"host-class-95da083e15eebd1c","sample_count":3,"timeout_ms":120000,"allow_privileged_cache_control":false,"command":{"program":"/home/ec2-user/cdf-bench/repo/target/release/cdf-p3-lab","args":["reference-worker","/home/ec2-user/cdf-bench/repo/target/cdf-benchmarks/g4-native-duckdb-20260718092526/duckdb-native-ingest-reference.json"],"environment":{},"current_dir":"/home/ec2-user/cdf-bench/repo"},"reference":{"kind":"internal","name":"duckdb","version":"1.10504.0","semantic_work":"native persistent CREATE TABLE AS SELECT from 12 local TLC Parquet files"},"bias":[{"code":"omits_cdf_evidence","description":"omits CDF package manifest receipts checkpoints normalizer provenance and destination commit gate"}]}